tralda/__init__.py
tralda/cograph/ClusterDeletion.py
tralda/cograph/Cograph.py
tralda/cograph/CographEditor.py
tralda/cograph/__init__.py
tralda/datastructures/AVLTree.py
tralda/datastructures/DoublyLinkedList.py
tralda/datastructures/LinkedList.py
tralda/datastructures/Partition.py
tralda/datastructures/Tree.py
tralda/datastructures/__init__.py
tralda/datastructures/hdtgraph/DynamicGraph.py
tralda/datastructures/hdtgraph/ETTree.py
tralda/datastructures/hdtgraph/__init__.py
tralda/supertree/Build.py
tralda/supertree/BuildST.py
tralda/supertree/CommonRefinement.py
tralda/supertree/LooseConsensus.py
tralda/supertree/__init__.py
tralda/tools/GraphTools.py
tralda/tools/TreeTools.py
tralda/tools/__init__.py
tralda-1.1.0.dist-info/LICENSE
tralda-1.1.0.dist-info/METADATA
tralda-1.1.0.dist-info/WHEEL
tralda-1.1.0.dist-info/top_level.txt
tralda-1.1.0.dist-info/RECORD
