Metadata-Version: 2.1
Name: tralda
Version: 1.1.0
Summary: A library for tree data structures and algorithms
Home-page: https://github.com/david-schaller/tralda
Author: David Schaller
Author-email: sdavid@bioinf.uni-leipzig.de
Project-URL: Bug Tracker, https://github.com/david-schaller/tralda/issues
Classifier: Programming Language :: Python :: 3
Classifier: License :: OSI Approved :: MIT License
Classifier: Operating System :: OS Independent
Requires-Python: >=3.7
License-File: LICENSE
Requires-Dist: numpy
Requires-Dist: networkx
